README.md
ohcg/__init__.py
ohcg/main.py
ohcg/openapi_models.py
ohcg/parser.py
ohcg/templates/base_model.jinja2
ohcg/templates/client.jinja2
ohcg/templates/enum_model.jinja2
ohcg/templates/model.jinja2
ohcg/templates/models.jinja2
ohcg/templates/operation.jinja2
ohcg/utils.py
ohcg-0.1.2.dist-info/entry_points.txt
ohcg-0.1.2.dist-info/LICENSE.txt
ohcg-0.1.2.dist-info/WHEEL
ohcg-0.1.2.dist-info/METADATA
ohcg-0.1.2.dist-info/RECORD
