Metadata-Version: 2.1
Name: ohcg
Version: 0.1.2
Summary: OpenAPI3 HTTP client generator
Home-page: https://github.com/pylakey/ohcg
License: MIT
Author: Pylakey
Author-email: pylakey@protonmail.com
Requires-Python: >=3.9,<4.0
Classifier: Framework :: AsyncIO
Classifier: License :: OSI Approved :: MIT License
Classifier: Operating System :: OS Independent
Classifier: Programming Language :: Python :: 3
Classifier: Programming Language :: Python :: 3.10
Classifier: Programming Language :: Python :: 3.9
Classifier: Topic :: Software Development :: Libraries :: Python Modules
Classifier: Typing :: Typed
Requires-Dist: httpx (>=0.19.0,<0.20.0)
Requires-Dist: jinja2 (>=3.0.1,<4.0.0)
Requires-Dist: pydantic[email] (>=1.8.2,<2.0.0)
Requires-Dist: pydash (>=5.0.2,<6.0.0)
Requires-Dist: typer[all] (>=0.4.0,<0.5.0)
Project-URL: Repository, https://github.com/pylakey/ohcg
